{
  "Arabic": "عربي",
  "home": "الرئيسية",
  "features": "الميزات",
  "how_it_work": "كيف يعمل",
  "screen_shoot": "لقطة الشاشة",
  "note": "ملاحظة",
  "contact_us": "اتصل بنا",
  "get_free_download": "احصل على تنزيل مجاني لتطبيق",
  "quiz_app": "Quiz",
  "reader_distracted": "من الحقائق الثابتة منذ فترة طويلة أن القارئ سوف يصرف انتباهه عن المحتوى",
  "download_on": "تحميل على",
  "play_store": "المتجر",
  "available_on": "متاح على",
  "google_play": "جوجل بلاي",
  "Friendly_Online_Support": "دعم ودود عبر الإنترنت",
  "Providing_round_the_clock_technical_support_to_assist_you_with_any_inquiries": "توفير دعم فني متاح على مدار الساعة لمساعدتك في أي استفسارات.",
  "Unlimited_Features": "ميزات غير محدودة",
  "Enjoy_limitless_possibilities_to_customize_your_experience": "استمتع بإمكانيات غير محدودة لتخصيص تجربتك.",
  "Modular_and_Switchable_Component": "مكون معياري وقابل للتبديل",
  "Easily_switch_between_layouts_and_even_demos": "تبديل بين التخطيطات وحتى العروض التوضيحية بسهولة.",
  "High_Resolution": "دقة عالية",
  "Get_high_quality_images_and_videos": "احصل على جودة صور وفيديو عالية الدقة.",
  "Social_Sharing": "مشاركة اجتماعية",
  "Easily_share_content_across_social_media_platforms": "سهولة مشاركة المحتوى عبر منصات التواصل الاجتماعي.",
  "Use_on_Any_Device": "استخدم على أي جهاز",
  "Compatibility_with_all_devices_for_a_seamless_experience": "توافق مع جميع الأجهزة لضمان تجربة سلسة.",
  "Creative_Design": "التصميم الإبداعي",
  "Attractive_and_innovative_design_that_meets_your_needs": "تصميم جذاب وابتكاري يلبي احتياجاتك.",
  "Providing_professional_value_objectively_with_varied_web_readiness_Collaborative_wireless_customer_service_without_targeted_incentives_for_change_Collaboration": "تقديم قيمة احترافية بموضوعية مع جاهزية متنوعة للويب. نقل خدمة العملاء اللاسلكية بشكل تعاوني دون محفزات موجهة نحو الهدف للتغيير. التعاون.",
  "Application_Features": "ميزات التطبيق"
}
